setup.py
character_reverse/Character.py
character_reverse/__init__.py
character_reverse.egg-info/PKG-INFO
character_reverse.egg-info/SOURCES.txt
character_reverse.egg-info/dependency_links.txt
character_reverse.egg-info/not-zip-safe
character_reverse.egg-info/top_level.txt