Metadata-Version: 1.0
Name: character-reverse
Version: 0.1
Summary: Reverse a string
Home-page: UNKNOWN
Author: UNKNOWN
Author-email: UNKNOWN
License: UNKNOWN
Platform: UNKNOWN
